MANIFEST.in
README.md
setup.cfg
setup.py
bltk.egg-info/PKG-INFO
bltk.egg-info/SOURCES.txt
bltk.egg-info/dependency_links.txt
bltk.egg-info/requires.txt
bltk.egg-info/top_level.txt
bltk/data/__init__.py
bltk/data/pos_tagger.pkl
bltk/langtools/__init__.py
bltk/langtools/banglachars.py
bltk/langtools/chunker.py
bltk/langtools/pos_tagger.py
bltk/langtools/stemmer.py
bltk/langtools/stopwords.py
bltk/langtools/taggertools.py
bltk/langtools/tokenizer.py