Metadata-Version: 2.1
Name: bltk
Version: 1.2
Summary: A lightweight but robust toolkit for Bengali Natural Language Processing.
Home-page: https://github.com/saimoncse19/bltk
Author: Saimon Hossain
Author-email: saimoncse19@gmail.com
Maintainer: Saimon Hossain
Maintainer-email: saimoncse19@gmail.com
License: MIT
Download-URL: https://github.com/saimoncse19/bltk/archive/v1.2.tar.gz
Keywords: pos-tagger,pos tagger,phrase chunker,phrase-chunker,stemmer,bengali,natural language processing,Machine learning,NLP
Platform: UNKNOWN
Classifier: Development Status :: 5 - Production/Stable
Classifier: Intended Audience :: Developers
Classifier: Intended Audience :: Education
Classifier: Natural Language :: English
Classifier: Natural Language :: Bengali
Classifier: License :: OSI Approved :: MIT License
Classifier: Programming Language :: Python :: 3
Classifier: Programming Language :: Python :: 3.6
Classifier: Programming Language :: Python :: 3.7
Classifier: Programming Language :: Python :: 3.8
Classifier: Programming Language :: Python :: 3 :: Only
Classifier: Operating System :: OS Independent
Requires-Python: >=3.6
